snowpylot/__init__.py
snowpylot/caaml_parser.py
snowpylot/core_info.py
snowpylot/layer.py
snowpylot/snow_pit.py
snowpylot/snow_profile.py
snowpylot/stability_tests.py
snowpylot/whumpf_data.py
snowpylot-1.1.3.dist-info/licenses/LICENSE
snowpylot-1.1.3.dist-info/METADATA
snowpylot-1.1.3.dist-info/WHEEL
snowpylot-1.1.3.dist-info/top_level.txt
snowpylot-1.1.3.dist-info/RECORD
