Metadata-Version: 2.4
Name: snowpylot
Version: 1.1.3
Summary: A Python library for working CAAML.XML files from SnowPilot
Home-page: https://github.com/connellymk/snowpylot
Author: Mary Kate Connelly
Author-email: Mary Kate Connelly <connellymarykate@gmail.com>
License: MIT License
Project-URL: Homepage, https://github.com/connellymk/snowpylot
Project-URL: Documentation, https://connellymk.github.io/snowpylot
Keywords: snowpit,caaml,snowpilot
Classifier: Programming Language :: Python :: 3
Classifier: License :: OSI Approved :: MIT License
Classifier: Operating System :: OS Independent
Requires-Python: >=3.7
License-File: LICENSE
Requires-Dist: sphinx>=7.0.0
Requires-Dist: sphinx-rtd-theme>=2.0.0
Requires-Dist: sphinx-autodoc-typehints>=1.25.0
Requires-Dist: IPython>=8.0.0
Provides-Extra: docs
Requires-Dist: sphinx>=7.0.0; extra == "docs"
Requires-Dist: sphinx-rtd-theme>=2.0.0; extra == "docs"
Requires-Dist: sphinx-autodoc-typehints>=1.25.0; extra == "docs"
Requires-Dist: IPython>=8.0.0; extra == "docs"
Dynamic: license-file
